extras_require-0.5.0.dist-info/LICENSE
extras_require-0.5.0.dist-info/METADATA
extras_require-0.5.0.dist-info/WHEEL
extras_require-0.5.0.dist-info/entry_points.txt
sphinxcontrib/extras_require/__init__.py
sphinxcontrib/extras_require/directive.py
sphinxcontrib/extras_require/purger.py
sphinxcontrib/extras_require/py.typed
sphinxcontrib/extras_require/sources.py
extras_require-0.5.0.dist-info/RECORD
