Metadata-Version: 2.1
Name: extras-require
Version: 0.5.0
Summary: Display a warning at the top of module documentation that it has additional requirements.
Author-email: Dominic Davis-Foster <dominic@davis-foster.co.uk>
License: BSD-3-Clause
Keywords: documentation,requirements,sphinx,sphinx-extension
Home-page: https://github.com/sphinx-toolbox/extras_require
Project-URL: Issue Tracker, https://github.com/sphinx-toolbox/extras_require/issues
Project-URL: Source Code, https://github.com/sphinx-toolbox/extras_require
Project-URL: Documentation, https://extras-require.readthedocs.io/en/latest
Platform: Windows
Platform: macOS
Platform: Linux
Classifier: Development Status :: 4 - Beta
Classifier: Framework :: Sphinx :: Extension
Classifier: Intended Audience :: Developers
Classifier: License :: OSI Approved :: BSD License
Classifier: Operating System :: OS Independent
Classifier: Programming Language :: Python
Classifier: Programming Language :: Python :: 3 :: Only
Classifier: Programming Language :: Python :: 3.6
Classifier: Programming Language :: Python :: 3.7
Classifier: Programming Language :: Python :: 3.8
Classifier: Programming Language :: Python :: 3.9
Classifier: Programming Language :: Python :: 3.10
Classifier: Programming Language :: Python :: 3.11
Classifier: Programming Language :: Python :: Implementation :: CPython
Classifier: Programming Language :: Python :: Implementation :: PyPy
Classifier: Topic :: Documentation
Classifier: Topic :: Documentation :: Sphinx
Classifier: Topic :: Software Development :: Documentation
Classifier: Topic :: Utilities
Classifier: Typing :: Typed
Requires-Python: >=3.6
Requires-Dist: docutils>=0.16
Requires-Dist: domdf-python-tools>=0.7.1
Requires-Dist: packaging>=20.4
Requires-Dist: setuptools>=49.2.0
Requires-Dist: shippinglabel>=0.10.0
Requires-Dist: sphinx>=3.3.0
Requires-Dist: sphinx-prompt>=1.1.0
Requires-Dist: sphinx-toolbox>=2.13.0
